psmgr/__init__.py
psmgr/__version__.py
psmgr/cli.py
psmgr/core.py
psmgr/secure_key/__init__.py
psmgr-1.2.0.dist-info/licenses/LICENSE
psmgr-1.2.0.dist-info/METADATA
psmgr-1.2.0.dist-info/WHEEL
psmgr-1.2.0.dist-info/entry_points.txt
psmgr-1.2.0.dist-info/top_level.txt
psmgr-1.2.0.dist-info/RECORD
